mcp_pandoc_md2pptx/__init__.py
mcp_pandoc_md2pptx/diagram.lua
mcp_pandoc_md2pptx/server.py
mcp_pandoc_md2pptx-0.1.1.dist-info/METADATA
mcp_pandoc_md2pptx-0.1.1.dist-info/WHEEL
mcp_pandoc_md2pptx-0.1.1.dist-info/entry_points.txt
mcp_pandoc_md2pptx-0.1.1.dist-info/licenses/LICENSE
mcp_pandoc_md2pptx-0.1.1.dist-info/RECORD
