Metadata-Version: 2.4
Name: mcp-pandoc-md2pptx
Version: 0.1.1
Summary: MCP to interface with pandoc to convert files to different formats with enhanced features like Mermaid diagram conversion and defaults file support.
License-File: LICENSE
Requires-Python: >=3.10
Requires-Dist: mcp>=1.1.0
Requires-Dist: pandoc>=2.4
Requires-Dist: pandocfilters>=1.5.0
Requires-Dist: panflute>=2.3.1
Requires-Dist: pypandoc>=1.14
Requires-Dist: pyyaml>=6.0.2
